langchain_salesforce/__init__.py
langchain_salesforce/py.typed
langchain_salesforce/tools.py
langchain_salesforce-0.2.2.dist-info/METADATA
langchain_salesforce-0.2.2.dist-info/WHEEL
langchain_salesforce-0.2.2.dist-info/licenses/LICENSE
langchain_salesforce-0.2.2.dist-info/RECORD
