Metadata-Version: 2.4
Name: langchain-salesforce
Version: 0.2.2
Summary: An integration package connecting Salesforce and LangChain
Project-URL: Repository, https://github.com/colesmcintosh/langchain-salesforce
Project-URL: Source Code, https://github.com/colesmcintosh/langchain-salesforce
Project-URL: Release Notes, https://github.com/colesmcintosh/langchain-salesforce/releases
Author-email: Cole McIntosh <colemcintosh6@gmail.com>
License-Expression: MIT
License-File: LICENSE
Keywords: ai,crm,langchain,llm,salesforce
Classifier: Development Status :: 3 - Alpha
Classifier: Intended Audience :: Developers
Classifier: License :: OSI Approved :: MIT License
Classifier: Programming Language :: Python :: 3
Classifier: Programming Language :: Python :: 3.9
Classifier: Programming Language :: Python :: 3.10
Classifier: Programming Language :: Python :: 3.11
Classifier: Topic :: Software Development :: Libraries :: Python Modules
Requires-Python: <4.0,>=3.9
Requires-Dist: langchain-core>=0.3.15
Requires-Dist: simple-salesforce>=1.12.6
